<?xml version="1.0" encoding="utf-8"?>
<PointLine>
  <Object>
    <ObjectType>Point</ObjectType>
    <x>-4.36809826</x>
    <y>2.09827042</y>
    <z>0</z>
    <id>0</id>
    <fixed>false</fixed>
    <name>A</name>
    <displayName>true</displayName>
    <active>true</active>
  </Object>
  <Object>
    <ObjectType>Point</ObjectType>
    <x>-1.90562356</x>
    <y>1.95379913</y>
    <z>0</z>
    <id>1</id>
    <fixed>false</fixed>
    <name>B</name>
    <displayName>true</displayName>
    <active>true</active>
  </Object>
  <Object>
    <ObjectType>Point</ObjectType>
    <x>-3.261103</x>
    <y>-0.1054678</y>
    <z>0</z>
    <id>2</id>
    <fixed>false</fixed>
    <name>C</name>
    <displayName>true</displayName>
    <active>true</active>
  </Object>
  <Object>
    <ObjectType>Point</ObjectType>
    <x>-0.235385925</x>
    <y>-0.127535939</y>
    <z>0</z>
    <id>3</id>
    <fixed>false</fixed>
    <name>D</name>
    <displayName>true</displayName>
    <active>true</active>
  </Object>
  <Object>
    <ObjectType>Point</ObjectType>
    <x>0.7315682</x>
    <y>2.35916853</y>
    <z>0</z>
    <id>4</id>
    <fixed>false</fixed>
    <name>E</name>
    <displayName>true</displayName>
    <active>true</active>
  </Object>
  <Object>
    <ObjectType>Point</ObjectType>
    <x>-1.76759493</x>
    <y>-2.73632622</y>
    <z>0</z>
    <id>5</id>
    <fixed>false</fixed>
    <name>F</name>
    <displayName>true</displayName>
    <active>true</active>
  </Object>
  <Object>
    <ObjectType>Module</ObjectType>
    <Type>28</Type>
    <Object1Id>0</Object1Id>
    <Object2Id>2</Object2Id>
    <Object3Id>1</Object3Id>
    <Object4Id>-1</Object4Id>
    <Ratio1>1</Ratio1>
    <Ratio2>1</Ratio2>
    <Constant>1.57079637</Constant>
    <ShowConstant>false</ShowConstant>
    <FixAngle>false</FixAngle>
    <FixRatio>true</FixRatio>
    <Parameter>0.1</Parameter>
    <ParaWeight>0.2</ParaWeight>
    <PolygonOption>0</PolygonOption>
    <id>3000</id>
    <name>三角形</name>
    <active>true</active>
  </Object>
  <Object>
    <ObjectType>Module</ObjectType>
    <Type>28</Type>
    <Object1Id>4</Object1Id>
    <Object2Id>1</Object2Id>
    <Object3Id>3</Object3Id>
    <Object4Id>-1</Object4Id>
    <Ratio1>1</Ratio1>
    <Ratio2>1</Ratio2>
    <Constant>1.57079637</Constant>
    <ShowConstant>false</ShowConstant>
    <FixAngle>false</FixAngle>
    <FixRatio>true</FixRatio>
    <Parameter>0.1</Parameter>
    <ParaWeight>0.2</ParaWeight>
    <PolygonOption>0</PolygonOption>
    <id>3001</id>
    <name>三角形</name>
    <active>true</active>
  </Object>
  <Object>
    <ObjectType>Module</ObjectType>
    <Type>28</Type>
    <Object1Id>3</Object1Id>
    <Object2Id>2</Object2Id>
    <Object3Id>5</Object3Id>
    <Object4Id>-1</Object4Id>
    <Ratio1>1</Ratio1>
    <Ratio2>1</Ratio2>
    <Constant>1.57079637</Constant>
    <ShowConstant>false</ShowConstant>
    <FixAngle>false</FixAngle>
    <FixRatio>true</FixRatio>
    <Parameter>0.1</Parameter>
    <ParaWeight>0.2</ParaWeight>
    <PolygonOption>0</PolygonOption>
    <id>3002</id>
    <name>三角形</name>
    <active>true</active>
  </Object>
  <Object>
    <ObjectType>Module</ObjectType>
    <Type>28</Type>
    <Object1Id>1</Object1Id>
    <Object2Id>2</Object2Id>
    <Object3Id>3</Object3Id>
    <Object4Id>-1</Object4Id>
    <Ratio1>1</Ratio1>
    <Ratio2>1</Ratio2>
    <Constant>1.57079637</Constant>
    <ShowConstant>false</ShowConstant>
    <FixAngle>false</FixAngle>
    <FixRatio>true</FixRatio>
    <Parameter>0.1</Parameter>
    <ParaWeight>0.2</ParaWeight>
    <PolygonOption>1</PolygonOption>
    <id>3003</id>
    <name>三角形</name>
    <active>true</active>
  </Object>
</PointLine>